pgcopy/__init__.py
pgcopy/copy.py
pgcopy/errors/__init__.py
pgcopy/errors/py2.py
pgcopy/errors/py3.py
pgcopy/util.py
pgcopy/version.py
pgcopy_standalone-1.6.0.dist-info/LICENSE.txt
pgcopy_standalone-1.6.0.dist-info/METADATA
pgcopy_standalone-1.6.0.dist-info/WHEEL
pgcopy_standalone-1.6.0.dist-info/RECORD
