Metadata-Version: 2.1
Name: pgcopy-standalone
Version: 1.6.0
Summary: Fast db insert with postgresql binary copy (fork of pgcopy) without psycopg2 dependency
License: MIT
Author: Aryeh Leib Taurog
Author-email: python@aryehleib.com
Requires-Python: >=3.10,<4.0
Classifier: License :: OSI Approved :: MIT License
Classifier: Programming Language :: Python :: 3
Classifier: Programming Language :: Python :: 3.10
Classifier: Programming Language :: Python :: 3.11
Classifier: Programming Language :: Python :: 3.12
Requires-Dist: pytz (>=2023.3.post1,<2024.0)
